mlflow_mltf_gateway/__about__.py
mlflow_mltf_gateway/__init__.py
mlflow_mltf_gateway/data_classes.py
mlflow_mltf_gateway/gateway_client.py
mlflow_mltf_gateway/gateway_server.py
mlflow_mltf_gateway/oauth_client.py
mlflow_mltf_gateway/project_packer.py
mlflow_mltf_gateway/utils.py
mlflow_mltf_gateway/adapters/LocalAdapter.py
mlflow_mltf_gateway/adapters/RESTAdapter.py
mlflow_mltf_gateway/adapters/__init__.py
mlflow_mltf_gateway/adapters/base.py
mlflow_mltf_gateway/backends/GatewayBackend.py
mlflow_mltf_gateway/backends/__init__.py
mlflow_mltf_gateway/executors/__init__.py
mlflow_mltf_gateway/executors/base.py
mlflow_mltf_gateway/executors/local_executor.py
mlflow_mltf_gateway/executors/slurm_executor.py
mlflow_mltf_gateway/executors/ssam_executor.py
mlflow_mltf_gateway/flaskapp/__init__.py
mlflow_mltf_gateway/flaskapp/app.py
mlflow_mltf_gateway/flaskapp/constants.py
mlflow_mltf_gateway/flaskapp/extensions.py
mlflow_mltf_gateway/flaskapp/jwt_decoder.py
mlflow_mltf_gateway/flaskapp/utils.py
mlflow_mltf_gateway/flaskapp/api_views/__init__.py
mlflow_mltf_gateway/flaskapp/api_views/gateway_api.py
mlflow_mltf_gateway/flaskapp/api_views/token_api.py
mlflow_mltf_gateway/flaskapp/models/__init__.py
mlflow_mltf_gateway/flaskapp/models/token.py
mlflow_mltf_gateway/flaskapp/models/user.py
mlflow_mltf_gateway/flaskapp/static/style.css
mlflow_mltf_gateway/flaskapp/templates/base.html
mlflow_mltf_gateway/flaskapp/templates/landing.html
mlflow_mltf_gateway/flaskapp/templates/token.html
mlflow_mltf_gateway/flaskapp/views/__init__.py
mlflow_mltf_gateway/flaskapp/views/auth.py
mlflow_mltf_gateway/flaskapp/views/token.py
mlflow_mltf_gateway/resources/__init__.py
mlflow_mltf_gateway/resources/inside.sh
mlflow_mltf_gateway/resources/mltf-hello-world.tar.gz
mlflow_mltf_gateway/resources/outside.sh
mlflow_mltf_gateway/resources/slurm-wrapper.sh
mlflow_mltf_gateway/resources/test/__init__.py
mlflow_mltf_gateway/resources/test/inside-noop.sh
mltf_gateway-0.1.4.dist-info/METADATA
mltf_gateway-0.1.4.dist-info/WHEEL
mltf_gateway-0.1.4.dist-info/entry_points.txt
mltf_gateway-0.1.4.dist-info/licenses/LICENSE.txt
mltf_gateway-0.1.4.dist-info/RECORD
