Metadata-Version: 2.4
Name: mltf-gateway
Version: 0.1.4
Project-URL: Documentation, https://github.com/accre/mltf-gateway#readme
Project-URL: Issues, https://github.com/accre/mltf-gateway/issues
Project-URL: Source, https://github.com/accre/mltf-gateway
Author-email: Andrew Melo <andrew.melo@gmail.com>, Prasanna Koirala <pkoiralap@gmail.com>
License-Expression: MIT
License-File: LICENSE.txt
Classifier: Development Status :: 4 - Beta
Classifier: Programming Language :: Python
Classifier: Programming Language :: Python :: 3.8
Classifier: Programming Language :: Python :: 3.9
Classifier: Programming Language :: Python :: 3.10
Classifier: Programming Language :: Python :: 3.11
Classifier: Programming Language :: Python :: 3.12
Classifier: Programming Language :: Python :: Implementation :: CPython
Classifier: Programming Language :: Python :: Implementation :: PyPy
Requires-Python: >=3.8
Requires-Dist: argon2-cffi
Requires-Dist: black
Requires-Dist: cryptography
Requires-Dist: flask
Requires-Dist: flask-login
Requires-Dist: flask-sqlalchemy
Requires-Dist: gunicorn
Requires-Dist: jaraco-classes
Requires-Dist: jinja2
Requires-Dist: keyring>=20.0.0
Requires-Dist: mlflow-skinny
Requires-Dist: pycryptodome
Requires-Dist: pyjwt
Requires-Dist: python-dotenv
Requires-Dist: requests
Requires-Dist: tbump
